<annotation>
	<folder>海报图片</folder>
	<filename>timddg.jpg</filename>
	<path>C:\Users\YCKJ1413\Pictures\海报图片\timddg.jpg</path>
	<source>
		<database>Unknown</database>
	</source>
	<size>
		<width>550</width>
		<height>357</height>
		<depth>3</depth>
	</size>
	<segmented>0</segmented>
	<object>
		<name>bill</name>
		<pose>Unspecified</pose>
		<truncated>1</truncated>
		<difficult>0</difficult>
		<bndbox>
			<xmin>92</xmin>
			<ymin>1</ymin>
			<xmax>180</xmax>
			<ymax>161</ymax>
		</bndbox>
	</object>
	<object>
		<name>bill</name>
		<pose>Unspecified</pose>
		<truncated>1</truncated>
		<difficult>0</difficult>
		<bndbox>
			<xmin>184</xmin>
			<ymin>1</ymin>
			<xmax>289</xmax>
			<ymax>157</ymax>
		</bndbox>
	</object>
	<object>
		<name>bill</name>
		<pose>Unspecified</pose>
		<truncated>0</truncated>
		<difficult>0</difficult>
		<bndbox>
			<xmin>210</xmin>
			<ymin>199</ymin>
			<xmax>235</xmax>
			<ymax>244</ymax>
		</bndbox>
	</object>
	<object>
		<name>bill</name>
		<pose>Unspecified</pose>
		<truncated>1</truncated>
		<difficult>0</difficult>
		<bndbox>
			<xmin>296</xmin>
			<ymin>1</ymin>
			<xmax>550</xmax>
			<ymax>154</ymax>
		</bndbox>
	</object>
</annotation>
